llama_rs_python-0.0.2.dist-info/METADATA
llama_rs_python-0.0.2.dist-info/WHEEL
llama_rs_python-0.0.2.dist-info/license_files/LICENSE
llama_rs_python/__init__.py
llama_rs_python/__init__.pyi
llama_rs_python/py.typed
llama_rs_python/llama_rs_python.cpython-38-x86_64-linux-gnu.so
llama_rs_python-0.0.2.dist-info/RECORD
