Metadata-Version: 2.1
Name: llama-rs-python
Version: 0.0.2
Classifier: Programming Language :: Rust
Classifier: Programming Language :: Python :: Implementation :: CPython
Classifier: Programming Language :: Python :: Implementation :: PyPy
Classifier: Programming Language :: Python :: 3
Classifier: License :: OSI Approved :: MIT License
License-File: LICENSE
Summary: Unofficial python bindings for llama-rs. 🐍❤️🦀
Author: Lukas Kreussel
Requires-Python: >=3.7
Project-URL: Homepage, https://github.com/LLukas22/llama-rs-python
Project-URL: Bug Tracker, https://github.com/LLukas22/llama-rs-python/issues
